graph_matrix_jsp_env/__init__.py
graph_matrix_jsp_env/disjunctive_jsp_env.py
graph_matrix_jsp_env/logger.py
graph_matrix_jsp_env/visualisation.py
graph_matrix_jsp_env/wzl_iqs_banner.py
graph_matrix_jsp_env-0.3.2.dist-info/LICENSE
graph_matrix_jsp_env-0.3.2.dist-info/METADATA
graph_matrix_jsp_env-0.3.2.dist-info/WHEEL
graph_matrix_jsp_env-0.3.2.dist-info/top_level.txt
graph_matrix_jsp_env-0.3.2.dist-info/RECORD
