Metadata-Version: 2.2
Name: graph-matrix-jsp-env
Version: 0.3.2
Summary: An enviorment for job shop scheduling using the disjunctive graph apporach and the graph matrix datastructure.
Author: Alexander Nasuta
Author-email: Alexander Nasuta <alexander.nasuta@wzl-iqs.rwth-aachen.de>
License: MIT License
Project-URL: Homepage, https://github.com/Alexander-Nasuta/pypitemplate
Platform: unix
Platform: linux
Platform: osx
Platform: cygwin
Platform: win32
Classifier: License :: OSI Approved :: MIT License
Classifier: Programming Language :: Python
Classifier: Programming Language :: Python :: 3
Requires-Python: >=3.9
License-File: LICENSE
Requires-Dist: rich
Requires-Dist: numpy
Requires-Dist: gymnasium
Requires-Dist: matplotlib<3.9
Requires-Dist: jsp-vis
Provides-Extra: examples
Requires-Dist: stable_baselines3; extra == "examples"
Requires-Dist: sb3_contrib; extra == "examples"
Requires-Dist: jsp_instance_utils; extra == "examples"
Provides-Extra: dev
Requires-Dist: pip-tools; extra == "dev"
Requires-Dist: pytest; extra == "dev"
Requires-Dist: pytest-cov; extra == "dev"
Requires-Dist: mypy; extra == "dev"
Requires-Dist: flake8; extra == "dev"
Requires-Dist: stable_baselines3; extra == "dev"
Requires-Dist: sphinx; extra == "dev"
Requires-Dist: myst-parser; extra == "dev"
Requires-Dist: sphinx-autobuild; extra == "dev"
Requires-Dist: furo; extra == "dev"
Requires-Dist: twine; extra == "dev"
Requires-Dist: sphinx-copybutton; extra == "dev"
Requires-Dist: nbsphinx; extra == "dev"
